mercadopagovp/__init__.py
mercadopagovp/create_pix_payment.py
mercadopagovp/load_sdk.py
mercadopagovp/pix_payment.py
mercadopagovp/verify_pix_payment.py
mercadopagovp-0.4.5.1.dist-info/LICENSE
mercadopagovp-0.4.5.1.dist-info/METADATA
mercadopagovp-0.4.5.1.dist-info/WHEEL
mercadopagovp-0.4.5.1.dist-info/top_level.txt
mercadopagovp-0.4.5.1.dist-info/RECORD
