Metadata-Version: 2.2
Name: mercadopagovp
Version: 0.4.5.1
Summary: A library for managing PIX payments on MercadoPago
Home-page: https://github.com/reinanbr/pix_plugin_mp_py
Author: Reinan Br
Author-email: slimchatuba@gmail.com
License: MIT
Keywords: mercadopago pix payments
Classifier: Programming Language :: Python :: 3
Classifier: License :: OSI Approved :: MIT License
Classifier: Operating System :: OS Independent
Requires-Python: >=3.9
License-File: LICENSE
Requires-Dist: mercadopago
Requires-Dist: python-dotenv
Requires-Dist: qrcode
Requires-Dist: pillow
Requires-Dist: requests
Requires-Dist: kitano
Dynamic: author
Dynamic: author-email
Dynamic: classifier
Dynamic: description
Dynamic: description-content-type
Dynamic: home-page
Dynamic: keywords
Dynamic: license
Dynamic: requires-dist
Dynamic: requires-python
Dynamic: summary
